gestaostock/__init__.py
gestaostock/gestaostocks.py
projetoummads-0.1.2.dist-info/licenses/LICENSE
projetoummads-0.1.2.dist-info/METADATA
projetoummads-0.1.2.dist-info/WHEEL
projetoummads-0.1.2.dist-info/top_level.txt
projetoummads-0.1.2.dist-info/RECORD
