Metadata-Version: 2.4
Name: ProjetoUmMADS
Version: 0.1.2
Summary: Projeto de MADS - Grupo 7 - Gestão de Stocks
Home-page: https://github.com/JoaoPinheiro1311/ProjetoUmMADS
Author: JoaoPinheiro1311
Author-email: a040698@ipmaia.pt
Classifier: Programming Language :: Python :: 3
Classifier: License :: OSI Approved :: MIT License
Classifier: Operating System :: OS Independent
Requires-Python: >=3.6
License-File: LICENSE
Requires-Dist: matplotlib
Dynamic: author
Dynamic: author-email
Dynamic: classifier
Dynamic: description
Dynamic: description-content-type
Dynamic: home-page
Dynamic: license-file
Dynamic: requires-dist
Dynamic: requires-python
Dynamic: summary
